{
    "Title": "Automatic inference of code transforms for patch generation",
    "APR Tool Name": "Genesis",
    "Authors": [
        "Fan Long",
        "Peter Amidon",
        "Martin C. Rinard"
    ],
    "Year": "2017",
    "Venue": "FSE",
    "Repo URL": "http://www.cs.toronto.edu/~fanl/program_repair/genesis-rep",
    "Target Language": [
        "Java"
    ],
    "Used Dataset": [
        "20 NP+13 OOB+16 CC defects from 41 open source applications"
    ],
    "CCF Rank": "A",
    "Paper Category": "-",
    "Bibtex": "@inproceedings{DBLP:conf/sigsoft/LongAR17,\n  author       = {Fan Long and\n                  Peter Amidon and\n                  Martin C. Rinard},\n  editor       = {Eric Bodden and\n                  Wilhelm Sch{\\\"{a}}fer and\n                  Arie van Deursen and\n                  Andrea Zisman},\n  title        = {Automatic inference of code transforms for patch generation},\n  booktitle    = {Proceedings of the 2017 11th Joint Meeting on Foundations of Software\n                  Engineering, {ESEC/FSE} 2017, Paderborn, Germany, September 4-8, 2017},\n  pages        = {727--739},\n  publisher    = {{ACM}},\n  year         = {2017},\n  url          = {https://doi.org/10.1145/3106237.3106253},\n  doi          = {10.1145/3106237.3106253},\n  timestamp    = {Fri, 29 Apr 2022 19:55:45 +0200},\n  biburl       = {https://dblp.org/rec/conf/sigsoft/LongAR17.bib},\n  bibsource    = {dblp computer science bibliography, https://dblp.org}\n}",
    "Specification": "-",
    "Tool Category": "-",
    "Bug Types": "-"
}